vmxai_completion_client/__init__.py
vmxai_completion_client/protos/__init__.py
vmxai_completion_client/protos/completion/completion.proto
vmxai_completion_client/protos/completion/completion_pb2.py
vmxai_completion_client/protos/completion/completion_pb2.pyi
vmxai_completion_client/protos/completion/completion_pb2_grpc.py
vm_x_ai_completion_client-1.6.0.dist-info/METADATA
vm_x_ai_completion_client-1.6.0.dist-info/WHEEL
vm_x_ai_completion_client-1.6.0.dist-info/RECORD
