Metadata-Version: 2.1
Name: vm-x-ai-completion-client
Version: 1.6.0
Summary: VM-X AI Completion Client
Home-page: https://github.com/vm-x-ai/vm-x-ai-sdk
License: MIT
Keywords: VM-X,AI,Completion,Client,Python
Author: VM-X Engineering
Author-email: eng@vm-x.ai
Maintainer: VM-X Engineering
Maintainer-email: eng@vm-x.ai
Requires-Python: >=3.8,<4
Classifier: Intended Audience :: Developers
Classifier: License :: OSI Approved :: MIT License
Classifier: Programming Language :: Python :: 3
Classifier: Programming Language :: Python :: 3.8
Classifier: Programming Language :: Python :: 3.9
Classifier: Programming Language :: Python :: 3.10
Classifier: Programming Language :: Python :: 3.11
Classifier: Programming Language :: Python :: 3.12
Requires-Dist: cachetools (>=5.3.3,<6.0.0)
Requires-Dist: grpcio (>=1.62.2,<2.0.0)
Requires-Dist: protobuf (>=4.21.6,<5.0.0)
Requires-Dist: requests (>=2.31.0,<3.0.0)
Project-URL: Repository, https://github.com/vm-x-ai/vm-x-ai-sdk
